vr/__init__.py
vr/runners/__init__.py
vr/runners/base.py
vr/runners/image.py
vr/runners/templates/image.lxc
vr/runners/templates/precise.lxc
vr/runners/templates/proc.sh
vr/runners/uptester/uptester
vr/runners/uptester/uptester.go
vr.runners-4.0.0.dist-info/LICENSE
vr.runners-4.0.0.dist-info/METADATA
vr.runners-4.0.0.dist-info/WHEEL
vr.runners-4.0.0.dist-info/entry_points.txt
vr.runners-4.0.0.dist-info/top_level.txt
vr.runners-4.0.0.dist-info/RECORD
